pyFTracks/thermal_history.pyx
pyFTracks/age_calculations.py
pyFTracks/viewer.py
pyFTracks/thermal_history.cpython-36m-i386-linux-gnu.so
pyFTracks/structures.py
pyFTracks/utilities.py
pyFTracks/__init__.py
pyFTracks/annealing.pyx
pyFTracks/path_generators.py
pyFTracks/annealing.cpython-36m-i386-linux-gnu.so
pyFTracks/ressources/Miller.h5
pyFTracks/ressources/Gleadow.h5
pyFTracks/ressources/__init__.py
pyFTracks/radialplot/age_calculations.py
pyFTracks/radialplot/utilities.py
pyFTracks/radialplot/__init__.py
pyFTracks/radialplot/FTradialplot.py
pyFTracks/radialplot/radialplot.py
pyFTracks-0.2.8.dist-info/LICENCE
pyFTracks-0.2.8.dist-info/top_level.txt
pyFTracks-0.2.8.dist-info/RECORD
pyFTracks-0.2.8.dist-info/METADATA
pyFTracks-0.2.8.dist-info/WHEEL
