Metadata-Version: 2.1
Name: pyFTracks
Version: 0.2.8
Summary: Fission Track Modelling and Analysis with Python
Home-page: https://github.com/rbeucher/pyFTracks.git
Author: Romain Beucher
Author-email: romain.beucher@unimelb.edu.au
License: UNKNOWN
Keywords: geology thermochronology fission-tracks
Platform: UNKNOWN
Classifier: Development Status :: 2 - Pre-Alpha
Classifier: Intended Audience :: Science/Research
Classifier: Topic :: Software Development :: Build Tools
Classifier: License :: OSI Approved :: MIT License
Classifier: Programming Language :: Python :: 2
Classifier: Programming Language :: Python :: 2.7
Classifier: Programming Language :: Python :: 3.3
Classifier: Programming Language :: Python :: 3.4
Classifier: Programming Language :: Python :: 3.5
Classifier: Programming Language :: Python :: 3.6
Classifier: Programming Language :: Python :: 3.7
Requires-Dist: Cython (>=0.29.14)
Requires-Dist: matplotlib (>=3.1.1)
Requires-Dist: numpy
Requires-Dist: jupyter
Requires-Dist: scipy (>=1.3.2)
Requires-Dist: pandas (>=0.25.3)
Requires-Dist: tables (>=3.6.1)
